14. counters/counters.v
`timescale 1ns / 1ps

//modN counter uses N no. of states
//this below is simple decimal 10 state counter
module modn_counter(
    input clk, reset,
    output reg [3:0] count 
);
    //here it should only count till required, all other states should be discarded.
    always @(posedge clk or posedge reset) begin
        if (reset) begin
            count <= 4'b0000;   //reset to 0000
        end
        else if (count == 4'b1010) begin
            count <= 4'b0000; //counts till decimal 10, back to 0000 after reached it.
        end
        else 
            count <= count +1; //basic up counter
    end
endmodule

//this is a basic practice of how a overflow will looks like.....
//taking example of a clock
module modn_overflow(
    input clk, reset,
    output reg [3:0] seconds,   //10 states
    output reg [3:0] tens,      //6 satetes
    output reg [2:0] hrs        //6 states
);
    always @(posedge clk or posedge reset) begin
        if (reset) begin
            seconds <= 3'b000;      //reset all to 0000
            tens <= 3'b000;
            hrs <= 3'b000;
        end
        else if (seconds == 4'd9 && tens == 4'd5) begin
            seconds <= 4'b000;      //STRUCTURE MATTERS: first check hrs
            tens <= 4'b0000;
            hrs <= hrs + 1;
        end
        else if (seconds == 4'd9) begin
            seconds <= 4'b0000;     //second, check and update tens
            tens <= tens + 1;
        end 
        else                        //third update seconds
            seconds <= seconds +1;  //basic up counter   
    end
endmodule

//---------------------------------------------------------------------------------------------------------//

//this divides clock frequency or count, HIGH -> LOW
//this is similar to asynchronous counter however what matters is the output.
module frequency_divider_counter(
    input clk, reset,
    output reg by2_clkout,
    output reg by4_clkout,
    output reg by8_clkout
);  
    //each clock counter needs their own count... 
    //so it depends on that single counter for toggling and dividing the frequency
    reg [3:0] count2;
    reg [3:0] count4;
    reg [3:0] count8;
    always @(posedge clk or posedge reset) begin
        if (reset) begin            //reset all
            count2 <= 4'b0000;
            count4 <= 4'b0000;
            count8 <= 4'b0000;
            by2_clkout <= 1'b0;
            by4_clkout <= 1'b0;
            by8_clkout <= 1'b0;
        end
        else begin
            if (count2 == 1) begin      //2 clock cycles
                by2_clkout = ~by2_clkout;   // toggle
                count2 <= 4'd0;             // reset count
            end
            else    count2 <= count2 + 1;

            if (count4 == 3) begin      //4 clock cycles
                by4_clkout = ~by4_clkout;   //toggle
                count4 <= 4'd0;
            end
            else    count4 <= count4 + 1;
            if (count8 == 7) begin      //8 clock cyles
                by8_clkout = ~by8_clkout;   //toggle
                count8 <= 4'd0;
            end
            else    count8 <= count8 + 1;
            //This below code first two dividers were dependent on a single counter which resets after 
            //16 cycles, which caused them to stretched their own clkout similar to by8_clkout;  
            //my own mistake, and first try....  
            /*if (count == 4'd1)      by2_clkout <= ~by2_clkout;     
            if (count == 4'd3)      by4_clkout <= ~by4_clkout;
            if (count == 4'd7) begin
                by8_clkout <= ~by8_clkout;
                count <= 4'd0;      //resets the counter
            end
            else begin
            count <= count + 1;   //count
            end*/
        end
    end    
endmodule

//---------------------------------------------------------------------------------------------------------//

//like a shift register where only one bit is high
//basically, 0010 > 0100 
module ring_counter#(
//this time instead of explicitly describing output for 4 bits,
//i'll use parameters, which are constant that akes module reusable //describing
    parameter WIDTH = 4    //4 bit width -> is a name not keyword   //declaration
)(  input clk, reset, direction,
    output reg [WIDTH-1:0] count    //width minus one, 4-1=3,= reg [3:0] count
);
    wire valid = (count !=0 && (count & (count -1)) == 0);     //this makes sure the the sate is one hot or not all zero
    always @(posedge clk or posedge reset) begin
        if (reset) begin
            count <= {{(WIDTH-1){1'b0}},1'b1}; //width-1=4-1=3, {{3 times 1'b0}<concatenates> 1'b1}
        end 
        else if (!valid) begin
            count <= {{(WIDTH-1){1'b0}},1'b1};  //same as above, resets it back to op value
        end
        else if (direction) begin   //1 is left || 0 is right
            count <= {count[WIDTH-2:0],count[WIDTH-1]}; // count[2:0]<concatenates>count[3]       
            end
        else begin
            count <= {count[0],count[WIDTH-1:1]}; //count[3]<concatenates>count[2:0]
        end
    end
endmodule

//---------------------------------------------------------------------------------------------------------//

//this is same ring counter basically inverts the shifting bit.
//more sates than ring (2N) and multiple high bits allowed
module johnson_counter#(
    parameter WIDTH = 4)
(   input clk, reset, direction,
    output reg [WIDTH-1:0] count
    );
    always @(posedge clk or posedge reset) begin
    if (reset) begin
            count <= {{(WIDTH-1){1'b0}},1'b1}; //width-1=4-1=3, {{3 times 1'b0}<concatenates> 1'b1}
        end 
        else if (direction) begin   //1 is left || 0 is right
            count <= {count[WIDTH-2:0],~count[WIDTH-1]}; // new MSB = NOT old_LSB << shift left
            end
        else begin
            count <= {~count[0],count[WIDTH-1:1]}; //   new LSB = NOT old_MSB >> shift right
        end
    end

endmodule

14. counters/counters_tb.v
`timescale 1ns / 1ps

//I'll upload the .vcd file its simulation results

module counters_tb;

	//inputs
	reg clk;
	reg reset;
	reg direction;

	//outputs
	wire [3:0] modn_count;

	wire [3:0] modn60_secs;
	wire [3:0] modn60_tens;
	wire [2:0] modn60_hrs;

	wire FDC2_clkout;
	wire FDC4_clkout;
	wire FDC8_clkout;

	wire [3:0] countRC;

	wire [3:0] countJC;

	// Instantiate the Unit Under Test (UUT)
	modn_counter MDN (
		.clk(clk),
		.reset(reset),
		.count(modn_count)
	);
	modn_overflow MDN60(
		.clk(clk),
		.reset(reset),
		.seconds(modn60_secs),
		.tens(modn60_tens),
		.hrs(modn60_hrs)
	);
	frequency_divider_counter FDC(
		.clk(clk),
		.reset(reset),
		.by2_clkout(FDC2_clkout),
		.by4_clkout(FDC4_clkout),
		.by8_clkout(FDC8_clkout)
	);
	ring_counter #(
		.WIDTH(4)
	)RC4(
		.clk(clk),
		.reset(reset),
		.direction(direction),
		.count(countRC)
	);
	johnson_counter #(
		.WIDTH(4)
	)JC4(
		.clk(clk),
		.reset(reset),
		.direction(direction),
		.count(countJC)
	);

	always #5 clk = ~clk;

	initial begin
		$dumpfile ("counters_sim.vcd");
		$dumpvars (0, counters_tb);
		clk = 0;
		direction = 0;	//right shift
		reset = 1;
		#10;
		reset = 0;
		direction = 1;	//left shift
		/*#200;
		reset = 1;
		#10;
		reset = 0;*/
		#100;
		direction = 0;	//right shift
		#100;
		direction = 1;	//left shift
		#100;
		//forcing a value for wire just for simulation....
		force RC4.count = 4'b0110;
		force JC4.count = 4'b0110;
		#100;
		release RC4.count;
		release JC4.count;
		#20;
		#2000;
		$finish;
	end
      
endmodule

14. counters/counters_sim.vcd
$date
	Wed Jun 17 14:27:37 2026
$end
$version
	Icarus Verilog
$end
$timescale
	1ps
$end
$scope module counters_tb $end
$var wire 4 ! modn_count [3:0] $end
$var wire 4 " modn60_tens [3:0] $end
$var wire 4 # modn60_secs [3:0] $end
$var wire 3 $ modn60_hrs [2:0] $end
$var wire 4 % countRC [3:0] $end
$var wire 4 & countJC [3:0] $end
$var wire 1 ' FDC8_clkout $end
$var wire 1 ( FDC4_clkout $end
$var wire 1 ) FDC2_clkout $end
$var reg 1 * clk $end
$var reg 1 + direction $end
$var reg 1 , reset $end
$scope module FDC $end
$var wire 1 * clk $end
$var wire 1 , reset $end
$var reg 1 ) by2_clkout $end
$var reg 1 ( by4_clkout $end
$var reg 1 ' by8_clkout $end
$var reg 4 - count2 [3:0] $end
$var reg 4 . count4 [3:0] $end
$var reg 4 / count8 [3:0] $end
$upscope $end
$scope module JC4 $end
$var wire 1 * clk $end
$var wire 1 + direction $end
$var wire 1 , reset $end
$var parameter 32 0 WIDTH $end
$var reg 4 1 count [3:0] $end
$upscope $end
$scope module MDN $end
$var wire 1 * clk $end
$var wire 1 , reset $end
$var reg 4 2 count [3:0] $end
$upscope $end
$scope module MDN60 $end
$var wire 1 * clk $end
$var wire 1 , reset $end
$var reg 3 3 hrs [2:0] $end
$var reg 4 4 seconds [3:0] $end
$var reg 4 5 tens [3:0] $end
$upscope $end
$scope module RC4 $end
$var wire 1 * clk $end
$var wire 1 + direction $end
$var wire 1 , reset $end
$var wire 1 6 valid $end
$var parameter 32 7 WIDTH $end
$var reg 4 8 count [3:0] $end
$upscope $end
$upscope $end
$enddefinitions $end
$comment Show the parameter values. $end
$dumpall
b100 7
b100 0
$end
#0
$dumpvars
b1 8
16
b0 5
b0 4
b0 3
b0 2
b1 1
b0 /
b0 .
b0 -
1,
0+
0*
0)
0(
0'
b1 &
b1 %
b0 $
b0 #
b0 "
b0 !
$end
#5000
1*
#10000
0*
1+
0,
#15000
b1 !
b1 2
b1 #
b1 4
b1 /
b1 .
b1 -
b10 %
b10 8
b11 &
b11 1
1*
#20000
0*
#25000
b111 &
b111 1
b100 %
b100 8
b10 /
b10 .
b0 -
b10 #
b10 4
b10 !
b10 2
1)
1*
#30000
0*
#35000
b11 !
b11 2
b11 #
b11 4
b11 /
b11 .
b1 -
b1000 %
b1000 8
b1111 &
b1111 1
1*
#40000
0*
#45000
b1110 &
b1110 1
b1 %
b1 8
b100 /
b0 .
b0 -
b100 #
b100 4
b100 !
b100 2
1(
0)
1*
#50000
0*
#55000
b101 !
b101 2
b101 #
b101 4
b101 /
b1 .
b1 -
b10 %
b10 8
b1100 &
b1100 1
1*
#60000
0*
#65000
b1000 &
b1000 1
b100 %
b100 8
b110 /
b10 .
b0 -
b110 #
b110 4
b110 !
b110 2
1)
1*
#70000
0*
#75000
b111 !
b111 2
b111 #
b111 4
b111 /
b11 .
b1 -
b1000 %
b1000 8
b0 &
b0 1
1*
#80000
0*
#85000
b1 &
b1 1
b1 %
b1 8
b0 /
b0 .
b0 -
b1000 #
b1000 4
b1000 !
b1000 2
1'
0(
0)
1*
#90000
0*
#95000
b1001 !
b1001 2
b1001 #
b1001 4
b1 /
b1 .
b1 -
b10 %
b10 8
b11 &
b11 1
1*
#100000
0*
#105000
b111 &
b111 1
b100 %
b100 8
b10 /
b10 .
b0 -
b1 "
b1 5
b0 #
b0 4
b1010 !
b1010 2
1)
1*
#110000
0*
0+
#115000
b0 !
b0 2
b1 #
b1 4
b11 /
b11 .
b1 -
b10 %
b10 8
b11 &
b11 1
1*
#120000
0*
#125000
b1 &
b1 1
b1 %
b1 8
b100 /
b0 .
b0 -
b10 #
b10 4
b1 !
b1 2
1(
0)
1*
#130000
0*
#135000
b10 !
b10 2
b11 #
b11 4
b101 /
b1 .
b1 -
b1000 %
b1000 8
b0 &
b0 1
1*
#140000
0*
#145000
b1000 &
b1000 1
b100 %
b100 8
b110 /
b10 .
b0 -
b100 #
b100 4
b11 !
b11 2
1)
1*
#150000
0*
#155000
b100 !
b100 2
b101 #
b101 4
b111 /
b11 .
b1 -
b10 %
b10 8
b1100 &
b1100 1
1*
#160000
0*
#165000
b1110 &
b1110 1
b1 %
b1 8
b0 /
b0 .
b0 -
b110 #
b110 4
b101 !
b101 2
0'
0(
0)
1*
#170000
0*
#175000
b110 !
b110 2
b111 #
b111 4
b1 /
b1 .
b1 -
b1000 %
b1000 8
b1111 &
b1111 1
1*
#180000
0*
#185000
b111 &
b111 1
b100 %
b100 8
b10 /
b10 .
b0 -
b1000 #
b1000 4
b111 !
b111 2
1)
1*
#190000
0*
#195000
b1000 !
b1000 2
b1001 #
b1001 4
b11 /
b11 .
b1 -
b10 %
b10 8
b11 &
b11 1
1*
#200000
0*
#205000
b1 &
b1 1
b1 %
b1 8
b100 /
b0 .
b0 -
b10 "
b10 5
b0 #
b0 4
b1001 !
b1001 2
1(
0)
1*
#210000
0*
1+
#215000
b1010 !
b1010 2
b1 #
b1 4
b101 /
b1 .
b1 -
b10 %
b10 8
b11 &
b11 1
1*
#220000
0*
#225000
b111 &
b111 1
b100 %
b100 8
b110 /
b10 .
b0 -
b10 #
b10 4
b0 !
b0 2
1)
1*
#230000
0*
#235000
b1 !
b1 2
b11 #
b11 4
b111 /
b11 .
b1 -
b1000 %
b1000 8
b1111 &
b1111 1
1*
#240000
0*
#245000
b1110 &
b1110 1
b1 %
b1 8
b0 /
b0 .
b0 -
b100 #
b100 4
b10 !
b10 2
1'
0(
0)
1*
#250000
0*
#255000
b11 !
b11 2
b101 #
b101 4
b1 /
b1 .
b1 -
b10 %
b10 8
b1100 &
b1100 1
1*
#260000
0*
#265000
b1000 &
b1000 1
b100 %
b100 8
b10 /
b10 .
b0 -
b110 #
b110 4
b100 !
b100 2
1)
1*
#270000
0*
#275000
b101 !
b101 2
b111 #
b111 4
b11 /
b11 .
b1 -
b1000 %
b1000 8
b0 &
b0 1
1*
#280000
0*
#285000
b1 &
b1 1
b1 %
b1 8
b100 /
b0 .
b0 -
b1000 #
b1000 4
b110 !
b110 2
1(
0)
1*
#290000
0*
#295000
b111 !
b111 2
b1001 #
b1001 4
b101 /
b1 .
b1 -
b10 %
b10 8
b11 &
b11 1
1*
#300000
0*
#305000
b111 &
b111 1
b100 %
b100 8
b110 /
b10 .
b0 -
b11 "
b11 5
b0 #
b0 4
b1000 !
b1000 2
1)
1*
#310000
06
0*
b110 &
b110 1
b110 %
b110 8
#315000
b1001 !
b1001 2
b1 #
b1 4
b111 /
b11 .
b1 -
b110 %
b110 8
b110 &
b110 1
1*
#320000
0*
#325000
b0 /
b0 .
b0 -
b10 #
b10 4
b1010 !
b1010 2
0'
0(
0)
1*
#330000
0*
#335000
b0 !
b0 2
b11 #
b11 4
b1 /
b1 .
b1 -
1*
#340000
0*
#345000
b10 /
b10 .
b0 -
b100 #
b100 4
b1 !
b1 2
1)
1*
#350000
0*
#355000
b10 !
b10 2
b101 #
b101 4
b11 /
b11 .
b1 -
1*
#360000
0*
#365000
b100 /
b0 .
b0 -
b110 #
b110 4
b11 !
b11 2
1(
0)
1*
#370000
0*
#375000
b100 !
b100 2
b111 #
b111 4
b101 /
b1 .
b1 -
1*
#380000
0*
#385000
b110 /
b10 .
b0 -
b1000 #
b1000 4
b101 !
b101 2
1)
1*
#390000
0*
#395000
b110 !
b110 2
b1001 #
b1001 4
b111 /
b11 .
b1 -
1*
#400000
0*
#405000
b0 /
b0 .
b0 -
b100 "
b100 5
b0 #
b0 4
b111 !
b111 2
1'
0(
0)
1*
#410000
0*
b110 &
b110 1
b110 %
b110 8
#415000
16
b1000 !
b1000 2
b1 #
b1 4
b1 /
b1 .
b1 -
b1 %
b1 8
b1101 &
b1101 1
1*
#420000
0*
#425000
b1010 &
b1010 1
b10 %
b10 8
b10 /
b10 .
b0 -
b10 #
b10 4
b1001 !
b1001 2
1)
1*
#430000
0*
#435000
b1010 !
b1010 2
b11 #
b11 4
b11 /
b11 .
b1 -
b100 %
b100 8
b100 &
b100 1
1*
#440000
0*
#445000
b1001 &
b1001 1
b1000 %
b1000 8
b100 /
b0 .
b0 -
b100 #
b100 4
b0 !
b0 2
1(
0)
1*
#450000
0*
#455000
b1 !
b1 2
b101 #
b101 4
b101 /
b1 .
b1 -
b1 %
b1 8
b10 &
b10 1
1*
#460000
0*
#465000
b101 &
b101 1
b10 %
b10 8
b110 /
b10 .
b0 -
b110 #
b110 4
b10 !
b10 2
1)
1*
#470000
0*
#475000
b11 !
b11 2
b111 #
b111 4
b111 /
b11 .
b1 -
b100 %
b100 8
b1011 &
b1011 1
1*
#480000
0*
#485000
b110 &
b110 1
b1000 %
b1000 8
b0 /
b0 .
b0 -
b1000 #
b1000 4
b100 !
b100 2
0'
0(
0)
1*
#490000
0*
#495000
b101 !
b101 2
b1001 #
b1001 4
b1 /
b1 .
b1 -
b1 %
b1 8
b1101 &
b1101 1
1*
#500000
0*
#505000
b1010 &
b1010 1
b10 %
b10 8
b10 /
b10 .
b0 -
b101 "
b101 5
b0 #
b0 4
b110 !
b110 2
1)
1*
#510000
0*
#515000
b111 !
b111 2
b1 #
b1 4
b11 /
b11 .
b1 -
b100 %
b100 8
b100 &
b100 1
1*
#520000
0*
#525000
b1001 &
b1001 1
b1000 %
b1000 8
b100 /
b0 .
b0 -
b10 #
b10 4
b1000 !
b1000 2
1(
0)
1*
#530000
0*
#535000
b1001 !
b1001 2
b11 #
b11 4
b101 /
b1 .
b1 -
b1 %
b1 8
b10 &
b10 1
1*
#540000
0*
#545000
b101 &
b101 1
b10 %
b10 8
b110 /
b10 .
b0 -
b100 #
b100 4
b1010 !
b1010 2
1)
1*
#550000
0*
#555000
b0 !
b0 2
b101 #
b101 4
b111 /
b11 .
b1 -
b100 %
b100 8
b1011 &
b1011 1
1*
#560000
0*
#565000
b110 &
b110 1
b1000 %
b1000 8
b0 /
b0 .
b0 -
b110 #
b110 4
b1 !
b1 2
1'
0(
0)
1*
#570000
0*
#575000
b10 !
b10 2
b111 #
b111 4
b1 /
b1 .
b1 -
b1 %
b1 8
b1101 &
b1101 1
1*
#580000
0*
#585000
b1010 &
b1010 1
b10 %
b10 8
b10 /
b10 .
b0 -
b1000 #
b1000 4
b11 !
b11 2
1)
1*
#590000
0*
#595000
b100 !
b100 2
b1001 #
b1001 4
b11 /
b11 .
b1 -
b100 %
b100 8
b100 &
b100 1
1*
#600000
0*
#605000
b1001 &
b1001 1
b1000 %
b1000 8
b100 /
b0 .
b0 -
b1 $
b1 3
b0 "
b0 5
b0 #
b0 4
b101 !
b101 2
1(
0)
1*
#610000
0*
#615000
b110 !
b110 2
b1 #
b1 4
b101 /
b1 .
b1 -
b1 %
b1 8
b10 &
b10 1
1*
#620000
0*
#625000
b101 &
b101 1
b10 %
b10 8
b110 /
b10 .
b0 -
b10 #
b10 4
b111 !
b111 2
1)
1*
#630000
0*
#635000
b1000 !
b1000 2
b11 #
b11 4
b111 /
b11 .
b1 -
b100 %
b100 8
b1011 &
b1011 1
1*
#640000
0*
#645000
b110 &
b110 1
b1000 %
b1000 8
b0 /
b0 .
b0 -
b100 #
b100 4
b1001 !
b1001 2
0'
0(
0)
1*
#650000
0*
#655000
b1010 !
b1010 2
b101 #
b101 4
b1 /
b1 .
b1 -
b1 %
b1 8
b1101 &
b1101 1
1*
#660000
0*
#665000
b1010 &
b1010 1
b10 %
b10 8
b10 /
b10 .
b0 -
b110 #
b110 4
b0 !
b0 2
1)
1*
#670000
0*
#675000
b1 !
b1 2
b111 #
b111 4
b11 /
b11 .
b1 -
b100 %
b100 8
b100 &
b100 1
1*
#680000
0*
#685000
b1001 &
b1001 1
b1000 %
b1000 8
b100 /
b0 .
b0 -
b1000 #
b1000 4
b10 !
b10 2
1(
0)
1*
#690000
0*
#695000
b11 !
b11 2
b1001 #
b1001 4
b101 /
b1 .
b1 -
b1 %
b1 8
b10 &
b10 1
1*
#700000
0*
#705000
b101 &
b101 1
b10 %
b10 8
b110 /
b10 .
b0 -
b1 "
b1 5
b0 #
b0 4
b100 !
b100 2
1)
1*
#710000
0*
#715000
b101 !
b101 2
b1 #
b1 4
b111 /
b11 .
b1 -
b100 %
b100 8
b1011 &
b1011 1
1*
#720000
0*
#725000
b110 &
b110 1
b1000 %
b1000 8
b0 /
b0 .
b0 -
b10 #
b10 4
b110 !
b110 2
1'
0(
0)
1*
#730000
0*
#735000
b111 !
b111 2
b11 #
b11 4
b1 /
b1 .
b1 -
b1 %
b1 8
b1101 &
b1101 1
1*
#740000
0*
#745000
b1010 &
b1010 1
b10 %
b10 8
b10 /
b10 .
b0 -
b100 #
b100 4
b1000 !
b1000 2
1)
1*
#750000
0*
#755000
b1001 !
b1001 2
b101 #
b101 4
b11 /
b11 .
b1 -
b100 %
b100 8
b100 &
b100 1
1*
#760000
0*
#765000
b1001 &
b1001 1
b1000 %
b1000 8
b100 /
b0 .
b0 -
b110 #
b110 4
b1010 !
b1010 2
1(
0)
1*
#770000
0*
#775000
b0 !
b0 2
b111 #
b111 4
b101 /
b1 .
b1 -
b1 %
b1 8
b10 &
b10 1
1*
#780000
0*
#785000
b101 &
b101 1
b10 %
b10 8
b110 /
b10 .
b0 -
b1000 #
b1000 4
b1 !
b1 2
1)
1*
#790000
0*
#795000
b10 !
b10 2
b1001 #
b1001 4
b111 /
b11 .
b1 -
b100 %
b100 8
b1011 &
b1011 1
1*
#800000
0*
#805000
b110 &
b110 1
b1000 %
b1000 8
b0 /
b0 .
b0 -
b10 "
b10 5
b0 #
b0 4
b11 !
b11 2
0'
0(
0)
1*
#810000
0*
#815000
b100 !
b100 2
b1 #
b1 4
b1 /
b1 .
b1 -
b1 %
b1 8
b1101 &
b1101 1
1*
#820000
0*
#825000
b1010 &
b1010 1
b10 %
b10 8
b10 /
b10 .
b0 -
b10 #
b10 4
b101 !
b101 2
1)
1*
#830000
0*
#835000
b110 !
b110 2
b11 #
b11 4
b11 /
b11 .
b1 -
b100 %
b100 8
b100 &
b100 1
1*
#840000
0*
#845000
b1001 &
b1001 1
b1000 %
b1000 8
b100 /
b0 .
b0 -
b100 #
b100 4
b111 !
b111 2
1(
0)
1*
#850000
0*
#855000
b1000 !
b1000 2
b101 #
b101 4
b101 /
b1 .
b1 -
b1 %
b1 8
b10 &
b10 1
1*
#860000
0*
#865000
b101 &
b101 1
b10 %
b10 8
b110 /
b10 .
b0 -
b110 #
b110 4
b1001 !
b1001 2
1)
1*
#870000
0*
#875000
b1010 !
b1010 2
b111 #
b111 4
b111 /
b11 .
b1 -
b100 %
b100 8
b1011 &
b1011 1
1*
#880000
0*
#885000
b110 &
b110 1
b1000 %
b1000 8
b0 /
b0 .
b0 -
b1000 #
b1000 4
b0 !
b0 2
1'
0(
0)
1*
#890000
0*
#895000
b1 !
b1 2
b1001 #
b1001 4
b1 /
b1 .
b1 -
b1 %
b1 8
b1101 &
b1101 1
1*
#900000
0*
#905000
b1010 &
b1010 1
b10 %
b10 8
b10 /
b10 .
b0 -
b11 "
b11 5
b0 #
b0 4
b10 !
b10 2
1)
1*
#910000
0*
#915000
b11 !
b11 2
b1 #
b1 4
b11 /
b11 .
b1 -
b100 %
b100 8
b100 &
b100 1
1*
#920000
0*
#925000
b1001 &
b1001 1
b1000 %
b1000 8
b100 /
b0 .
b0 -
b10 #
b10 4
b100 !
b100 2
1(
0)
1*
#930000
0*
#935000
b101 !
b101 2
b11 #
b11 4
b101 /
b1 .
b1 -
b1 %
b1 8
b10 &
b10 1
1*
#940000
0*
#945000
b101 &
b101 1
b10 %
b10 8
b110 /
b10 .
b0 -
b100 #
b100 4
b110 !
b110 2
1)
1*
#950000
0*
#955000
b111 !
b111 2
b101 #
b101 4
b111 /
b11 .
b1 -
b100 %
b100 8
b1011 &
b1011 1
1*
#960000
0*
#965000
b110 &
b110 1
b1000 %
b1000 8
b0 /
b0 .
b0 -
b110 #
b110 4
b1000 !
b1000 2
0'
0(
0)
1*
#970000
0*
#975000
b1001 !
b1001 2
b111 #
b111 4
b1 /
b1 .
b1 -
b1 %
b1 8
b1101 &
b1101 1
1*
#980000
0*
#985000
b1010 &
b1010 1
b10 %
b10 8
b10 /
b10 .
b0 -
b1000 #
b1000 4
b1010 !
b1010 2
1)
1*
#990000
0*
#995000
b0 !
b0 2
b1001 #
b1001 4
b11 /
b11 .
b1 -
b100 %
b100 8
b100 &
b100 1
1*
#1000000
0*
#1005000
b1001 &
b1001 1
b1000 %
b1000 8
b100 /
b0 .
b0 -
b100 "
b100 5
b0 #
b0 4
b1 !
b1 2
1(
0)
1*
#1010000
0*
#1015000
b10 !
b10 2
b1 #
b1 4
b101 /
b1 .
b1 -
b1 %
b1 8
b10 &
b10 1
1*
#1020000
0*
#1025000
b101 &
b101 1
b10 %
b10 8
b110 /
b10 .
b0 -
b10 #
b10 4
b11 !
b11 2
1)
1*
#1030000
0*
#1035000
b100 !
b100 2
b11 #
b11 4
b111 /
b11 .
b1 -
b100 %
b100 8
b1011 &
b1011 1
1*
#1040000
0*
#1045000
b110 &
b110 1
b1000 %
b1000 8
b0 /
b0 .
b0 -
b100 #
b100 4
b101 !
b101 2
1'
0(
0)
1*
#1050000
0*
#1055000
b110 !
b110 2
b101 #
b101 4
b1 /
b1 .
b1 -
b1 %
b1 8
b1101 &
b1101 1
1*
#1060000
0*
#1065000
b1010 &
b1010 1
b10 %
b10 8
b10 /
b10 .
b0 -
b110 #
b110 4
b111 !
b111 2
1)
1*
#1070000
0*
#1075000
b1000 !
b1000 2
b111 #
b111 4
b11 /
b11 .
b1 -
b100 %
b100 8
b100 &
b100 1
1*
#1080000
0*
#1085000
b1001 &
b1001 1
b1000 %
b1000 8
b100 /
b0 .
b0 -
b1000 #
b1000 4
b1001 !
b1001 2
1(
0)
1*
#1090000
0*
#1095000
b1010 !
b1010 2
b1001 #
b1001 4
b101 /
b1 .
b1 -
b1 %
b1 8
b10 &
b10 1
1*
#1100000
0*
#1105000
b101 &
b101 1
b10 %
b10 8
b110 /
b10 .
b0 -
b101 "
b101 5
b0 #
b0 4
b0 !
b0 2
1)
1*
#1110000
0*
#1115000
b1 !
b1 2
b1 #
b1 4
b111 /
b11 .
b1 -
b100 %
b100 8
b1011 &
b1011 1
1*
#1120000
0*
#1125000
b110 &
b110 1
b1000 %
b1000 8
b0 /
b0 .
b0 -
b10 #
b10 4
b10 !
b10 2
0'
0(
0)
1*
#1130000
0*
#1135000
b11 !
b11 2
b11 #
b11 4
b1 /
b1 .
b1 -
b1 %
b1 8
b1101 &
b1101 1
1*
#1140000
0*
#1145000
b1010 &
b1010 1
b10 %
b10 8
b10 /
b10 .
b0 -
b100 #
b100 4
b100 !
b100 2
1)
1*
#1150000
0*
#1155000
b101 !
b101 2
b101 #
b101 4
b11 /
b11 .
b1 -
b100 %
b100 8
b100 &
b100 1
1*
#1160000
0*
#1165000
b1001 &
b1001 1
b1000 %
b1000 8
b100 /
b0 .
b0 -
b110 #
b110 4
b110 !
b110 2
1(
0)
1*
#1170000
0*
#1175000
b111 !
b111 2
b111 #
b111 4
b101 /
b1 .
b1 -
b1 %
b1 8
b10 &
b10 1
1*
#1180000
0*
#1185000
b101 &
b101 1
b10 %
b10 8
b110 /
b10 .
b0 -
b1000 #
b1000 4
b1000 !
b1000 2
1)
1*
#1190000
0*
#1195000
b1001 !
b1001 2
b1001 #
b1001 4
b111 /
b11 .
b1 -
b100 %
b100 8
b1011 &
b1011 1
1*
#1200000
0*
#1205000
b110 &
b110 1
b1000 %
b1000 8
b0 /
b0 .
b0 -
b10 $
b10 3
b0 "
b0 5
b0 #
b0 4
b1010 !
b1010 2
1'
0(
0)
1*
#1210000
0*
#1215000
b0 !
b0 2
b1 #
b1 4
b1 /
b1 .
b1 -
b1 %
b1 8
b1101 &
b1101 1
1*
#1220000
0*
#1225000
b1010 &
b1010 1
b10 %
b10 8
b10 /
b10 .
b0 -
b10 #
b10 4
b1 !
b1 2
1)
1*
#1230000
0*
#1235000
b10 !
b10 2
b11 #
b11 4
b11 /
b11 .
b1 -
b100 %
b100 8
b100 &
b100 1
1*
#1240000
0*
#1245000
b1001 &
b1001 1
b1000 %
b1000 8
b100 /
b0 .
b0 -
b100 #
b100 4
b11 !
b11 2
1(
0)
1*
#1250000
0*
#1255000
b100 !
b100 2
b101 #
b101 4
b101 /
b1 .
b1 -
b1 %
b1 8
b10 &
b10 1
1*
#1260000
0*
#1265000
b101 &
b101 1
b10 %
b10 8
b110 /
b10 .
b0 -
b110 #
b110 4
b101 !
b101 2
1)
1*
#1270000
0*
#1275000
b110 !
b110 2
b111 #
b111 4
b111 /
b11 .
b1 -
b100 %
b100 8
b1011 &
b1011 1
1*
#1280000
0*
#1285000
b110 &
b110 1
b1000 %
b1000 8
b0 /
b0 .
b0 -
b1000 #
b1000 4
b111 !
b111 2
0'
0(
0)
1*
#1290000
0*
#1295000
b1000 !
b1000 2
b1001 #
b1001 4
b1 /
b1 .
b1 -
b1 %
b1 8
b1101 &
b1101 1
1*
#1300000
0*
#1305000
b1010 &
b1010 1
b10 %
b10 8
b10 /
b10 .
b0 -
b1 "
b1 5
b0 #
b0 4
b1001 !
b1001 2
1)
1*
#1310000
0*
#1315000
b1010 !
b1010 2
b1 #
b1 4
b11 /
b11 .
b1 -
b100 %
b100 8
b100 &
b100 1
1*
#1320000
0*
#1325000
b1001 &
b1001 1
b1000 %
b1000 8
b100 /
b0 .
b0 -
b10 #
b10 4
b0 !
b0 2
1(
0)
1*
#1330000
0*
#1335000
b1 !
b1 2
b11 #
b11 4
b101 /
b1 .
b1 -
b1 %
b1 8
b10 &
b10 1
1*
#1340000
0*
#1345000
b101 &
b101 1
b10 %
b10 8
b110 /
b10 .
b0 -
b100 #
b100 4
b10 !
b10 2
1)
1*
#1350000
0*
#1355000
b11 !
b11 2
b101 #
b101 4
b111 /
b11 .
b1 -
b100 %
b100 8
b1011 &
b1011 1
1*
#1360000
0*
#1365000
b110 &
b110 1
b1000 %
b1000 8
b0 /
b0 .
b0 -
b110 #
b110 4
b100 !
b100 2
1'
0(
0)
1*
#1370000
0*
#1375000
b101 !
b101 2
b111 #
b111 4
b1 /
b1 .
b1 -
b1 %
b1 8
b1101 &
b1101 1
1*
#1380000
0*
#1385000
b1010 &
b1010 1
b10 %
b10 8
b10 /
b10 .
b0 -
b1000 #
b1000 4
b110 !
b110 2
1)
1*
#1390000
0*
#1395000
b111 !
b111 2
b1001 #
b1001 4
b11 /
b11 .
b1 -
b100 %
b100 8
b100 &
b100 1
1*
#1400000
0*
#1405000
b1001 &
b1001 1
b1000 %
b1000 8
b100 /
b0 .
b0 -
b10 "
b10 5
b0 #
b0 4
b1000 !
b1000 2
1(
0)
1*
#1410000
0*
#1415000
b1001 !
b1001 2
b1 #
b1 4
b101 /
b1 .
b1 -
b1 %
b1 8
b10 &
b10 1
1*
#1420000
0*
#1425000
b101 &
b101 1
b10 %
b10 8
b110 /
b10 .
b0 -
b10 #
b10 4
b1010 !
b1010 2
1)
1*
#1430000
0*
#1435000
b0 !
b0 2
b11 #
b11 4
b111 /
b11 .
b1 -
b100 %
b100 8
b1011 &
b1011 1
1*
#1440000
0*
#1445000
b110 &
b110 1
b1000 %
b1000 8
b0 /
b0 .
b0 -
b100 #
b100 4
b1 !
b1 2
0'
0(
0)
1*
#1450000
0*
#1455000
b10 !
b10 2
b101 #
b101 4
b1 /
b1 .
b1 -
b1 %
b1 8
b1101 &
b1101 1
1*
#1460000
0*
